{
  "_class": "shapeGroup",
  "booleanOperation": 0,
  "clippingMaskMode": 0,
  "do_objectID": "A5F03E8E-846E-418F-8809-A83E4304F77D",
  "exportOptions": {
    "_class": "exportOptions",
    "exportFormats": [
    ],
    "includedLayerIds": [
    ],
    "layerOptions": 0,
    "shouldTrim": false
  },
  "frame": {
    "_class": "rect",
    "constrainProportions": false,
    "height": 26.80315825159091,
    "width": 39.85987533433717,
    "x": 0.1077956733782022,
    "y": 8.020346205974215
  },
  "hasClickThrough": false,
  "hasClippingMask": false,
  "isFixedToViewport": false,
  "isFlippedHorizontal": false,
  "isFlippedVertical": false,
  "isLocked": false,
  "isVisible": true,
  "layerListExpandedType": 0,
  "layers": [
    {
      "class": "shapePath",
      "id": "E0963B1D-D56F-45C8-A7D2-3D3D24434B43"
    },
    {
      "class": "shapePath",
      "id": "02E9F656-280E-4AC3-AA01-9443C34E5963"
    },
    {
      "class": "shapePath",
      "id": "3C94CA2A-D5A8-40E8-89E5-E5ED5614D195"
    },
    {
      "class": "shapePath",
      "id": "A0F3501F-0A7D-48A8-9A52-5C67E01FEE57"
    }
  ],
  "name": "Fill 1",
  "nameIsFixed": false,
  "resizingConstraint": 63,
  "resizingType": 0,
  "rotation": 0,
  "shouldBreakMaskChain": false,
  "style": {
    "_class": "style",
    "endMarkerType": 0,
    "fills": [
      {
        "_class": "fill",
        "color": {
          "_class": "color",
          "alpha": 1,
          "blue": 0.3333333333333333,
          "green": 0.8666666666666667,
          "red": 0
        },
        "fillType": 0,
        "isEnabled": true,
        "noiseIndex": 0,
        "noiseIntensity": 0,
        "patternFillType": 1,
        "patternTileScale": 1
      }
    ],
    "miterLimit": 10,
    "startMarkerType": 0,
    "windingRule": 1
  },
  "windingRule": 1
}