{
  "_class": "shapePath",
  "booleanOperation": -1,
  "clippingMaskMode": 0,
  "do_objectID": "750305A8-C061-436E-9BA9-4FA52D52FA1F",
  "edited": true,
  "exportOptions": {
    "_class": "exportOptions",
    "exportFormats": [
    ],
    "includedLayerIds": [
    ],
    "layerOptions": 0,
    "shouldTrim": false
  },
  "frame": {
    "_class": "rect",
    "constrainProportions": false,
    "height": 26.78208444197511,
    "width": 18.62905096660263,
    "x": -8.881784197001255e-15,
    "y": 0.02107380961578824
  },
  "hasClippingMask": false,
  "isClosed": false,
  "isFixedToViewport": false,
  "isFlippedHorizontal": false,
  "isFlippedVertical": false,
  "isLocked": false,
  "isVisible": true,
  "layerListExpandedType": 0,
  "name": "Path",
  "nameIsFixed": false,
  "pointRadiusBehaviour": 0,
  "points": [
    {
      "_class": "curvePoint",
      "cornerRadius": 0,
      "curveFrom": "{0.99569829950032707, 0.051323486431560192}",
      "curveMode": 4,
      "curveTo": "{0.99624027408650806, 0.10798867827851204}",
      "hasCurveFrom": true,
      "hasCurveTo": false,
      "point": "{0.99624027408650806, 0.10798867827851204}"
    },
    {
      "_class": "curvePoint",
      "cornerRadius": 0,
      "curveFrom": "{0.82923983826465708, 0.00045550226617117943}",
      "curveMode": 3,
      "curveTo": "{0.95143704162889342, 0.013943225340327464}",
      "hasCurveFrom": true,
      "hasCurveTo": true,
      "point": "{0.88420810518308568, 0.0065626762544069841}"
    },
    {
      "_class": "curvePoint",
      "cornerRadius": 0,
      "curveFrom": "{0.48283377053726123, -0.050270064947503169}",
      "curveMode": 4,
      "curveTo": "{0.78620705612190001, 0.018090071875549431}",
      "hasCurveFrom": true,
      "hasCurveTo": true,
      "point": "{0.75296594816947593, 0.046632104492723245}"
    },
    {
      "_class": "curvePoint",
      "cornerRadius": 0,
      "curveFrom": "{-0.030632952410450148, 0.24699600061979973}",
      "curveMode": 3,
      "curveTo": "{0.2427390288591568, 0.017855502778607417}",
      "hasCurveFrom": true,
      "hasCurveTo": true,
      "point": "{0.11701296874489882, 0.1232440470474802}"
    },
    {
      "_class": "curvePoint",
      "cornerRadius": 0,
      "curveFrom": "{0.20421065772154681, 0.65450116428202254}",
      "curveMode": 3,
      "curveTo": "{-0.038051982301280957, 0.41900216842015664}",
      "hasCurveFrom": true,
      "hasCurveTo": true,
      "point": "{0.091901479585187448, 0.54531762712334109}"
    },
    {
      "_class": "curvePoint",
      "cornerRadius": 0,
      "curveFrom": "{0.7378147475157989, 0.6639760803049235}",
      "curveMode": 4,
      "curveTo": "{0.44667804369915376, 0.74450030029796044}",
      "hasCurveFrom": true,
      "hasCurveTo": true,
      "point": "{0.73733299232808236, 0.64896365810064538}"
    },
    {
      "_class": "curvePoint",
      "cornerRadius": 0,
      "curveFrom": "{0.68836257749672181, 0.81894247870600501}",
      "curveMode": 3,
      "curveTo": "{0.73343077530758072, 0.68898282153247403}",
      "hasCurveFrom": true,
      "hasCurveTo": true,
      "point": "{0.72985374303878725, 0.69952167595936143}"
    },
    {
      "_class": "curvePoint",
      "cornerRadius": 0,
      "curveFrom": "{0.32274652165913914, 0.80038638764435532}",
      "curveMode": 3,
      "curveTo": "{0.5031999710979671, 0.86089683718760368}",
      "hasCurveFrom": true,
      "hasCurveTo": true,
      "point": "{0.3643340382387476, 0.81429298410590756}"
    },
    {
      "_class": "curvePoint",
      "cornerRadius": 0,
      "curveFrom": "{0.20692053065245083, 0.74911628502706595}",
      "curveMode": 2,
      "curveTo": "{0.28584407428007147, 0.77992861140392711}",
      "hasCurveFrom": true,
      "hasCurveTo": true,
      "point": "{0.24531641911343893, 0.76411195229584827}"
    },
    {
      "_class": "curvePoint",
      "cornerRadius": 0,
      "curveFrom": "{0.091058408006683869, 0.78412572274563663}",
      "curveMode": 2,
      "curveTo": "{0.16689871843292042, 0.74975297257590812}",
      "hasCurveFrom": true,
      "hasCurveTo": true,
      "point": "{0.1296229107833726, 0.76665870249121693}"
    },
    {
      "_class": "curvePoint",
      "cornerRadius": 0,
      "curveFrom": "{0.08136308485389368, 0.87343790640624464}",
      "curveMode": 2,
      "curveTo": "{0.073233466061181376, 0.80894815968273259}",
      "hasCurveFrom": true,
      "hasCurveTo": true,
      "point": "{0.077292253517690965, 0.84154488668990124}"
    },
    {
      "_class": "curvePoint",
      "cornerRadius": 0,
      "curveFrom": "{0.30523472058565204, 1.0019063743206453}",
      "curveMode": 3,
      "curveTo": "{0.10630595969790441, 0.89609057919662871}",
      "hasCurveFrom": true,
      "hasCurveTo": true,
      "point": "{0.14087189441654802, 0.91449587583881575}"
    },
    {
      "_class": "curvePoint",
      "cornerRadius": 0,
      "curveFrom": "{0.89003734295445247, 0.90947777265780971}",
      "curveMode": 2,
      "curveTo": "{0.50394669163892747, 1.0262010307896221}",
      "hasCurveFrom": true,
      "hasCurveTo": true,
      "point": "{0.6927465497049401, 0.96916723036176167}"
    },
    {
      "_class": "curvePoint",
      "cornerRadius": 0,
      "curveFrom": "{1.0049118674654012, 0.47132783197368433}",
      "curveMode": 3,
      "curveTo": "{0.98403982395759304, 0.79353361902655417}",
      "hasCurveFrom": true,
      "hasCurveTo": true,
      "point": "{0.993626752193147, 0.64535296950129062}"
    },
    {
      "_class": "curvePoint",
      "cornerRadius": 0,
      "curveFrom": "{0.99624027408650806, 0.10798867827851204}",
      "curveMode": 4,
      "curveTo": "{0.9981672948373731, 0.2824243117257666}",
      "hasCurveFrom": false,
      "hasCurveTo": true,
      "point": "{0.99624027408650806, 0.10798867827851204}"
    }
  ],
  "resizingConstraint": 63,
  "resizingType": 0,
  "rotation": 0,
  "shouldBreakMaskChain": false,
  "style": {
    "_class": "style",
    "endMarkerType": 0,
    "fills": [
      {
        "_class": "fill",
        "color": {
          "_class": "color",
          "alpha": 1,
          "blue": 0.3333333333333333,
          "green": 0.8666666666666667,
          "red": 0
        },
        "fillType": 0,
        "isEnabled": true,
        "noiseIndex": 0,
        "noiseIntensity": 0,
        "patternFillType": 1,
        "patternTileScale": 1
      }
    ],
    "miterLimit": 10,
    "startMarkerType": 0,
    "windingRule": 1
  }
}