{
  "_class": "group",
  "booleanOperation": 0,
  "clippingMaskMode": 0,
  "do_objectID": "79E68546-96A1-4BEE-810F-E920703609D8",
  "exportOptions": {
    "_class": "exportOptions",
    "exportFormats": [
    ],
    "includedLayerIds": [
    ],
    "layerOptions": 0,
    "shouldTrim": false
  },
  "frame": {
    "_class": "rect",
    "constrainProportions": false,
    "height": 46,
    "width": 156,
    "x": 0,
    "y": 108
  },
  "hasClickThrough": false,
  "hasClippingMask": false,
  "isFixedToViewport": false,
  "isFlippedHorizontal": false,
  "isFlippedVertical": false,
  "isLocked": false,
  "isVisible": true,
  "layerListExpandedType": 0,
  "layers": [
    {
      "class": "group",
      "id": "F177FF26-D4AD-4E78-8138-2E665974F6F3"
    },
    {
      "class": "shapePath",
      "id": "B6D9E382-C87F-4D6C-9A7E-89F7D7E65A3E"
    },
    {
      "class": "text",
      "id": "E5B1C7A3-419C-4E11-B4B7-E84E3573C45E"
    }
  ],
  "name": "drivingExp Copy 6",
  "nameIsFixed": true,
  "resizingConstraint": 63,
  "resizingType": 0,
  "rotation": 0,
  "shouldBreakMaskChain": false,
  "style": {
    "_class": "style",
    "endMarkerType": 0,
    "miterLimit": 10,
    "startMarkerType": 0,
    "windingRule": 1
  }
}